[{"consent":1,"gender":null,"alter":null,"beziehung":null,"eigene_attr":null,"partner_attr":null,"attr_vergleich":null,"erscheinung":null},
{"consent":1,"gender":1,"alter":32,"beziehung":2,"eigene_attr":null,"partner_attr":null,"attr_vergleich":null,"erscheinung":null},
{"consent":null,"gender":null,"alter":null,"beziehung":null,"eigene_attr":null,"partner_attr":null,"attr_vergleich":null,"erscheinung":null},
{"consent":1,"gender":2,"alter":22,"beziehung":2,"eigene_attr":1,"partner_attr":2,"attr_vergleich":2,"erscheinung":2},
{"consent":1,"gender":2,"alter":19,"beziehung":2,"eigene_attr":3,"partner_attr":5,"attr_vergleich":3,"erscheinung":3},
{"consent":1,"gender":2,"alter":37,"beziehung":1,"eigene_attr":1,"partner_attr":null,"attr_vergleich":null,"erscheinung":4},
{"consent":1,"gender":2,"alter":33,"beziehung":2,"eigene_attr":5,"partner_attr":5,"attr_vergleich":3,"erscheinung":4},
{"consent":1,"gender":2,"alter":22,"beziehung":2,"eigene_attr":2,"partner_attr":4,"attr_vergleich":2,"erscheinung":3},
{"consent":1,"gender":2,"alter":21,"beziehung":1,"eigene_attr":3,"partner_attr":null,"attr_vergleich":null,"erscheinung":4},
{"consent":1,"gender":2,"alter":19,"beziehung":2,"eigene_attr":3,"partner_attr":3,"attr_vergleich":1,"erscheinung":4},
{"consent":1,"gender":2,"alter":20,"beziehung":1,"eigene_attr":4,"partner_attr":null,"attr_vergleich":null,"erscheinung":4},
{"consent":null,"gender":null,"alter":null,"beziehung":null,"eigene_attr":null,"partner_attr":null,"attr_vergleich":null,"erscheinung":null},
{"consent":null,"gender":null,"alter":null,"beziehung":null,"eigene_attr":null,"partner_attr":null,"attr_vergleich":null,"erscheinung":null},
{"consent":1,"gender":1,"alter":31,"beziehung":1,"eigene_attr":4,"partner_attr":null,"attr_vergleich":null,"erscheinung":4},
{"consent":1,"gender":2,"alter":21,"beziehung":1,"eigene_attr":2,"partner_attr":null,"attr_vergleich":null,"erscheinung":3},
{"consent":1,"gender":1,"alter":20,"beziehung":2,"eigene_attr":4,"partner_attr":4,"attr_vergleich":3,"erscheinung":3},
{"consent":1,"gender":2,"alter":29,"beziehung":2,"eigene_attr":3,"partner_attr":3,"attr_vergleich":2,"erscheinung":4},
{"consent":1,"gender":1,"alter":20,"beziehung":1,"eigene_attr":3,"partner_attr":null,"attr_vergleich":null,"erscheinung":4},
{"consent":1,"gender":2,"alter":21,"beziehung":2,"eigene_attr":4,"partner_attr":4,"attr_vergleich":3,"erscheinung":3},
{"consent":1,"gender":2,"alter":24,"beziehung":1,"eigene_attr":5,"partner_attr":null,"attr_vergleich":null,"erscheinung":3},
{"consent":null,"gender":null,"alter":null,"beziehung":null,"eigene_attr":null,"partner_attr":null,"attr_vergleich":null,"erscheinung":null},
{"consent":null,"gender":null,"alter":null,"beziehung":null,"eigene_attr":null,"partner_attr":null,"attr_vergleich":null,"erscheinung":null},
{"consent":1,"gender":1,"alter":20,"beziehung":2,"eigene_attr":3,"partner_attr":5,"attr_vergleich":1,"erscheinung":3},
{"consent":1,"gender":2,"alter":21,"beziehung":2,"eigene_attr":4,"partner_attr":5,"attr_vergleich":1,"erscheinung":4},
{"consent":1,"gender":2,"alter":19,"beziehung":1,"eigene_attr":4,"partner_attr":null,"attr_vergleich":null,"erscheinung":4},
{"consent":1,"gender":2,"alter":19,"beziehung":1,"eigene_attr":4,"partner_attr":null,"attr_vergleich":null,"erscheinung":4},
{"consent":1,"gender":2,"alter":25,"beziehung":1,"eigene_attr":3,"partner_attr":null,"attr_vergleich":null,"erscheinung":4},
{"consent":1,"gender":2,"alter":21,"beziehung":1,"eigene_attr":3,"partner_attr":null,"attr_vergleich":null,"erscheinung":3},
{"consent":1,"gender":2,"alter":20,"beziehung":2,"eigene_attr":3,"partner_attr":2,"attr_vergleich":4,"erscheinung":2},
{"consent":1,"gender":2,"alter":19,"beziehung":2,"eigene_attr":4,"partner_attr":5,"attr_vergleich":1,"erscheinung":2},
{"consent":null,"gender":null,"alter":null,"beziehung":null,"eigene_attr":null,"partner_attr":null,"attr_vergleich":null,"erscheinung":null},
{"consent":1,"gender":1,"alter":21,"beziehung":1,"eigene_attr":4,"partner_attr":null,"attr_vergleich":null,"erscheinung":2},
{"consent":1,"gender":2,"alter":22,"beziehung":1,"eigene_attr":1,"partner_attr":null,"attr_vergleich":null,"erscheinung":2},
{"consent":1,"gender":2,"alter":19,"beziehung":2,"eigene_attr":3,"partner_attr":2,"attr_vergleich":4,"erscheinung":5}]